mercury_imgpprcs/__init__.py
mercury_imgpprcs/json_filter.py
mercury_imgpprcs/line_filter.py
mercury_imgpprcs/mercury_json.py
mercury_imgpprcs/mercury_line.py
mercury_imgpprcs-0.0.1.dist-info/LICENSE
mercury_imgpprcs-0.0.1.dist-info/METADATA
mercury_imgpprcs-0.0.1.dist-info/WHEEL
mercury_imgpprcs-0.0.1.dist-info/top_level.txt
mercury_imgpprcs-0.0.1.dist-info/RECORD
